{
  "version": "7",
  "dialect": "postgresql",
  "entries": [
    {
      "idx": 0,
      "version": "7",
      "when": 1756324893359,
      "tag": "0000_complex_sersi",
      "breakpoints": true
    },
    {
      "idx": 1,
      "version": "7",
      "when": 1756380935952,
      "tag": "0001_polite_onslaught",
      "breakpoints": true
    },
    {
      "idx": 2,
      "version": "7",
      "when": 1756393158565,
      "tag": "0002_normal_veda",
      "breakpoints": true
    },
    {
      "idx": 3,
      "version": "7",
      "when": 1756562454751,
      "tag": "0003_magenta_blob",
      "breakpoints": true
    },
    {
      "idx": 4,
      "version": "7",
      "when": 1756568956200,
      "tag": "0004_noisy_centennial",
      "breakpoints": true
    },
    {
      "idx": 5,
      "version": "7",
      "when": 1756728554278,
      "tag": "0005_soft_luckman",
      "breakpoints": true
    }
  ]
}